django_aws_s3_storage/__init__.py
django_aws_s3_storage/apps.py
django_aws_s3_storage/settings.py
django_aws_s3_storage/storage.py
django_aws_s3_storage/tests.py
django_aws_s3_storage/utils.py
django_aws_s3_storage-1.0.1.dist-info/METADATA
django_aws_s3_storage-1.0.1.dist-info/WHEEL
django_aws_s3_storage-1.0.1.dist-info/top_level.txt
django_aws_s3_storage-1.0.1.dist-info/RECORD
