Metadata-Version: 2.1
Name: django-aws-s3-storage
Version: 1.0.1
Summary: AWS S3 Bucket file storage system for Django applications
Home-page: UNKNOWN
Author: Gustavo Valentim
License: UNKNOWN
Platform: UNKNOWN
Requires-Python: >=3.6
Requires-Dist: django (>=2.1.0)
Requires-Dist: boto3 (~=1.16.56)
